assets/__init__.py
pyamazon/__init__.py
pyamazon/fetchProduct.py
pyamazon-1.0.3.dist-info/licenses/LICENSE
pyamazon-1.0.3.dist-info/METADATA
pyamazon-1.0.3.dist-info/WHEEL
pyamazon-1.0.3.dist-info/top_level.txt
pyamazon-1.0.3.dist-info/RECORD
