Metadata-Version: 2.4
Name: pyamazon
Version: 1.0.3
Summary: Python module to fetch product data from Amazon
Author: Shivanand Mishra
License: MIT
Project-URL: Source, https://github.com/xemishra/pyamazon
Project-URL: Issues, https://github.com/xemishra/pyamazon/issues
Classifier: Programming Language :: Python :: 3
Classifier: License :: OSI Approved :: MIT License
Classifier: Operating System :: OS Independent
Requires-Python: >=3.6
License-File: LICENSE
Dynamic: author
Dynamic: classifier
Dynamic: description
Dynamic: description-content-type
Dynamic: license
Dynamic: license-file
Dynamic: project-url
Dynamic: requires-python
Dynamic: summary
